{
  "hash": "d7a618d9",
  "configHash": "4db94833",
  "lockfileHash": "258c70fe",
  "browserHash": "20bd5d1e",
  "optimized": {
    "vue": {
      "src": "../../../../node_modules/vue/dist/vue.runtime.esm-bundler.js",
      "file": "vue.js",
      "fileHash": "6a93bad0",
      "needsInterop": false
    },
    "vitepress > @vue/devtools-api": {
      "src": "../../../../node_modules/@vue/devtools-api/dist/index.js",
      "file": "vitepress___@vue_devtools-api.js",
      "fileHash": "9b1221f8",
      "needsInterop": false
    },
    "vitepress > @vueuse/core": {
      "src": "../../../../node_modules/@vueuse/core/dist/index.js",
      "file": "vitepress___@vueuse_core.js",
      "fileHash": "d94c8fc5",
      "needsInterop": false
    }
  },
  "chunks": {
    "chunk-ADVWCYKY": {
      "file": "chunk-ADVWCYKY.js"
    }
  }
}